{"success": true, "date": "2026-03-03", "timezone": "Europe/Paris (CET)", "count": 96, "statistics": {"min": 0.91, "max": 193.24, "average": 59.32, "median": 46.81}, "prices": [{"timestamp": "2026-03-03T00:00:00+01:00", "spot_price": 42.44, "spot_price_eur_kwh": 0.04244, "turpe_eur_kwh": 0.0373, "accise_eur_kwh": 0.02998, "price_ht_eur_kwh": 0.10972, "price_ttc_eur_kwh": 0.13166}, {"timestamp": "2026-03-03T00:15:00+01:00", "spot_price": 56.95, "spot_price_eur_kwh": 0.05695, "turpe_eur_kwh": 0.0373, "accise_eur_kwh": 0.02998, "price_ht_eur_kwh": 0.12423, "price_ttc_eur_kwh": 0.14908}, {"timestamp": "2026-03-03T00:30:00+01:00", "spot_price": 48.41, "spot_price_eur_kwh": 0.04841, "turpe_eur_kwh": 0.0373, "accise_eur_kwh": 0.02998, "price_ht_eur_kwh": 0.11569, "price_ttc_eur_kwh": 0.13883}, {"timestamp": "2026-03-03T00:45:00+01:00", "spot_price": 32.84, "spot_price_eur_kwh": 0.03284, "turpe_eur_kwh": 0.0373, "accise_eur_kwh": 0.02998, "price_ht_eur_kwh": 0.10012, "price_ttc_eur_kwh": 0.12014}, {"timestamp": "2026-03-03T01:00:00+01:00", "spot_price": 62.82, "spot_price_eur_kwh": 0.06282, "turpe_eur_kwh": 0.0373, "accise_eur_kwh": 0.02998, "price_ht_eur_kwh": 0.1301, "price_ttc_eur_kwh": 0.15612}, {"timestamp": "2026-03-03T01:15:00+01:00", "spot_price": 44.65, "spot_price_eur_kwh": 0.04465, "turpe_eur_kwh": 0.0373, "accise_eur_kwh": 0.02998, "price_ht_eur_kwh": 0.11193, "price_ttc_eur_kwh": 0.13432}, {"timestamp": "2026-03-03T01:30:00+01:00", "spot_price": 57.28, "spot_price_eur_kwh": 0.05728, "turpe_eur_kwh": 0.0373, "accise_eur_kwh": 0.02998, "price_ht_eur_kwh": 0.12456, "price_ttc_eur_kwh": 0.14947}, {"timestamp": "2026-03-03T01:45:00+01:00", "spot_price": 44.01, "spot_price_eur_kwh": 0.04401, "turpe_eur_kwh": 0.0373, "accise_eur_kwh": 0.02998, "price_ht_eur_kwh": 0.11129, "price_ttc_eur_kwh": 0.13355}, {"timestamp": "2026-03-03T02:00:00+01:00", "spot_price": 63.44, "spot_price_eur_kwh": 0.06344, "turpe_eur_kwh": 0.0373, "accise_eur_kwh": 0.02998, "price_ht_eur_kwh": 0.13072, "price_ttc_eur_kwh": 0.15686}, {"timestamp": "2026-03-03T02:15:00+01:00", "spot_price": 44.81, "spot_price_eur_kwh": 0.04481, "turpe_eur_kwh": 0.0373, "accise_eur_kwh": 0.02998, "price_ht_eur_kwh": 0.11209, "price_ttc_eur_kwh": 0.13451}, {"timestamp": "2026-03-03T02:30:00+01:00", "spot_price": 37.36, "spot_price_eur_kwh": 0.03736, "turpe_eur_kwh": 0.0373, "accise_eur_kwh": 0.02998, "price_ht_eur_kwh": 0.10464, "price_ttc_eur_kwh": 0.12557}, {"timestamp": "2026-03-03T02:45:00+01:00", "spot_price": 30.26, "spot_price_eur_kwh": 0.03026, "turpe_eur_kwh": 0.0373, "accise_eur_kwh": 0.02998, "price_ht_eur_kwh": 0.09754, "price_ttc_eur_kwh": 0.11705}, {"timestamp": "2026-03-03T03:00:00+01:00", "spot_price": 37.52, "spot_price_eur_kwh": 0.03752, "turpe_eur_kwh": 0.0373, "accise_eur_kwh": 0.02998, "price_ht_eur_kwh": 0.1048, "price_ttc_eur_kwh": 0.12576}, {"timestamp": "2026-03-03T03:15:00+01:00", "spot_price": 28.81, "spot_price_eur_kwh": 0.02881, "turpe_eur_kwh": 0.0373, "accise_eur_kwh": 0.02998, "price_ht_eur_kwh": 0.09609, "price_ttc_eur_kwh": 0.11531}, {"timestamp": "2026-03-03T03:30:00+01:00", "spot_price": 28.17, "spot_price_eur_kwh": 0.02817, "turpe_eur_kwh": 0.0373, "accise_eur_kwh": 0.02998, "price_ht_eur_kwh": 0.09545, "price_ttc_eur_kwh": 0.11454}, {"timestamp": "2026-03-03T03:45:00+01:00", "spot_price": 23, "spot_price_eur_kwh": 0.023, "turpe_eur_kwh": 0.0373, "accise_eur_kwh": 0.02998, "price_ht_eur_kwh": 0.09028, "price_ttc_eur_kwh": 0.10834}, {"timestamp": "2026-03-03T04:00:00+01:00", "spot_price": 33.99, "spot_price_eur_kwh": 0.03399, "turpe_eur_kwh": 0.0373, "accise_eur_kwh": 0.02998, "price_ht_eur_kwh": 0.10127, "price_ttc_eur_kwh": 0.12152}, {"timestamp": "2026-03-03T04:15:00+01:00", "spot_price": 31.07, "spot_price_eur_kwh": 0.03107, "turpe_eur_kwh": 0.0373, "accise_eur_kwh": 0.02998, "price_ht_eur_kwh": 0.09835, "price_ttc_eur_kwh": 0.11802}, {"timestamp": "2026-03-03T04:30:00+01:00", "spot_price": 36.32, "spot_price_eur_kwh": 0.03632, "turpe_eur_kwh": 0.0373, "accise_eur_kwh": 0.02998, "price_ht_eur_kwh": 0.1036, "price_ttc_eur_kwh": 0.12432}, {"timestamp": "2026-03-03T04:45:00+01:00", "spot_price": 30.38, "spot_price_eur_kwh": 0.03038, "turpe_eur_kwh": 0.0373, "accise_eur_kwh": 0.02998, "price_ht_eur_kwh": 0.09766, "price_ttc_eur_kwh": 0.11719}, {"timestamp": "2026-03-03T05:00:00+01:00", "spot_price": 34.39, "spot_price_eur_kwh": 0.03439, "turpe_eur_kwh": 0.0373, "accise_eur_kwh": 0.02998, "price_ht_eur_kwh": 0.10167, "price_ttc_eur_kwh": 0.122}, {"timestamp": "2026-03-03T05:15:00+01:00", "spot_price": 36.83, "spot_price_eur_kwh": 0.03683, "turpe_eur_kwh": 0.0373, "accise_eur_kwh": 0.02998, "price_ht_eur_kwh": 0.10411, "price_ttc_eur_kwh": 0.12493}, {"timestamp": "2026-03-03T05:30:00+01:00", "spot_price": 53.63, "spot_price_eur_kwh": 0.05363, "turpe_eur_kwh": 0.0373, "accise_eur_kwh": 0.02998, "price_ht_eur_kwh": 0.12091, "price_ttc_eur_kwh": 0.14509}, {"timestamp": "2026-03-03T05:45:00+01:00", "spot_price": 55.11, "spot_price_eur_kwh": 0.05511, "turpe_eur_kwh": 0.0373, "accise_eur_kwh": 0.02998, "price_ht_eur_kwh": 0.12239, "price_ttc_eur_kwh": 0.14687}, {"timestamp": "2026-03-03T06:00:00+01:00", "spot_price": 69.48, "spot_price_eur_kwh": 0.06948, "turpe_eur_kwh": 0.0373, "accise_eur_kwh": 0.02998, "price_ht_eur_kwh": 0.13676, "price_ttc_eur_kwh": 0.16411}, {"timestamp": "2026-03-03T06:15:00+01:00", "spot_price": 78.06, "spot_price_eur_kwh": 0.07806, "turpe_eur_kwh": 0.0373, "accise_eur_kwh": 0.02998, "price_ht_eur_kwh": 0.14534, "price_ttc_eur_kwh": 0.17441}, {"timestamp": "2026-03-03T06:30:00+01:00", "spot_price": 84, "spot_price_eur_kwh": 0.084, "turpe_eur_kwh": 0.0373, "accise_eur_kwh": 0.02998, "price_ht_eur_kwh": 0.15128, "price_ttc_eur_kwh": 0.18154}, {"timestamp": "2026-03-03T06:45:00+01:00", "spot_price": 143.37, "spot_price_eur_kwh": 0.14337, "turpe_eur_kwh": 0.0373, "accise_eur_kwh": 0.02998, "price_ht_eur_kwh": 0.21065, "price_ttc_eur_kwh": 0.25278}, {"timestamp": "2026-03-03T07:00:00+01:00", "spot_price": 137.24, "spot_price_eur_kwh": 0.13724, "turpe_eur_kwh": 0.07, "accise_eur_kwh": 0.02998, "price_ht_eur_kwh": 0.23722, "price_ttc_eur_kwh": 0.28466}, {"timestamp": "2026-03-03T07:15:00+01:00", "spot_price": 152.03, "spot_price_eur_kwh": 0.15203, "turpe_eur_kwh": 0.07, "accise_eur_kwh": 0.02998, "price_ht_eur_kwh": 0.25201, "price_ttc_eur_kwh": 0.30241}, {"timestamp": "2026-03-03T07:30:00+01:00", "spot_price": 160.84, "spot_price_eur_kwh": 0.16084, "turpe_eur_kwh": 0.07, "accise_eur_kwh": 0.02998, "price_ht_eur_kwh": 0.26082, "price_ttc_eur_kwh": 0.31298}, {"timestamp": "2026-03-03T07:45:00+01:00", "spot_price": 132.93, "spot_price_eur_kwh": 0.13293, "turpe_eur_kwh": 0.07, "accise_eur_kwh": 0.02998, "price_ht_eur_kwh": 0.23291, "price_ttc_eur_kwh": 0.27949}, {"timestamp": "2026-03-03T08:00:00+01:00", "spot_price": 184.19, "spot_price_eur_kwh": 0.18419, "turpe_eur_kwh": 0.07, "accise_eur_kwh": 0.02998, "price_ht_eur_kwh": 0.28417, "price_ttc_eur_kwh": 0.341}, {"timestamp": "2026-03-03T08:15:00+01:00", "spot_price": 144.88, "spot_price_eur_kwh": 0.14488, "turpe_eur_kwh": 0.07, "accise_eur_kwh": 0.02998, "price_ht_eur_kwh": 0.24486, "price_ttc_eur_kwh": 0.29383}, {"timestamp": "2026-03-03T08:30:00+01:00", "spot_price": 123.28, "spot_price_eur_kwh": 0.12328, "turpe_eur_kwh": 0.07, "accise_eur_kwh": 0.02998, "price_ht_eur_kwh": 0.22326, "price_ttc_eur_kwh": 0.26791}, {"timestamp": "2026-03-03T08:45:00+01:00", "spot_price": 91.68, "spot_price_eur_kwh": 0.09168, "turpe_eur_kwh": 0.07, "accise_eur_kwh": 0.02998, "price_ht_eur_kwh": 0.19166, "price_ttc_eur_kwh": 0.22999}, {"timestamp": "2026-03-03T09:00:00+01:00", "spot_price": 129, "spot_price_eur_kwh": 0.129, "turpe_eur_kwh": 0.07, "accise_eur_kwh": 0.02998, "price_ht_eur_kwh": 0.22898, "price_ttc_eur_kwh": 0.27478}, {"timestamp": "2026-03-03T09:15:00+01:00", "spot_price": 87.75, "spot_price_eur_kwh": 0.08775, "turpe_eur_kwh": 0.07, "accise_eur_kwh": 0.02998, "price_ht_eur_kwh": 0.18773, "price_ttc_eur_kwh": 0.22528}, {"timestamp": "2026-03-03T09:30:00+01:00", "spot_price": 72.29, "spot_price_eur_kwh": 0.07229, "turpe_eur_kwh": 0.07, "accise_eur_kwh": 0.02998, "price_ht_eur_kwh": 0.17227, "price_ttc_eur_kwh": 0.20672}, {"timestamp": "2026-03-03T09:45:00+01:00", "spot_price": 43.16, "spot_price_eur_kwh": 0.04316, "turpe_eur_kwh": 0.07, "accise_eur_kwh": 0.02998, "price_ht_eur_kwh": 0.14314, "price_ttc_eur_kwh": 0.17177}, {"timestamp": "2026-03-03T10:00:00+01:00", "spot_price": 46.81, "spot_price_eur_kwh": 0.04681, "turpe_eur_kwh": 0.07, "accise_eur_kwh": 0.02998, "price_ht_eur_kwh": 0.14679, "price_ttc_eur_kwh": 0.17615}, {"timestamp": "2026-03-03T10:15:00+01:00", "spot_price": 43, "spot_price_eur_kwh": 0.043, "turpe_eur_kwh": 0.07, "accise_eur_kwh": 0.02998, "price_ht_eur_kwh": 0.14298, "price_ttc_eur_kwh": 0.17158}, {"timestamp": "2026-03-03T10:30:00+01:00", "spot_price": 27.28, "spot_price_eur_kwh": 0.02728, "turpe_eur_kwh": 0.07, "accise_eur_kwh": 0.02998, "price_ht_eur_kwh": 0.12726, "price_ttc_eur_kwh": 0.15271}, {"timestamp": "2026-03-03T10:45:00+01:00", "spot_price": 17.73, "spot_price_eur_kwh": 0.01773, "turpe_eur_kwh": 0.07, "accise_eur_kwh": 0.02998, "price_ht_eur_kwh": 0.11771, "price_ttc_eur_kwh": 0.14125}, {"timestamp": "2026-03-03T11:00:00+01:00", "spot_price": 29.71, "spot_price_eur_kwh": 0.02971, "turpe_eur_kwh": 0.07, "accise_eur_kwh": 0.02998, "price_ht_eur_kwh": 0.12969, "price_ttc_eur_kwh": 0.15563}, {"timestamp": "2026-03-03T11:15:00+01:00", "spot_price": 22.55, "spot_price_eur_kwh": 0.02255, "turpe_eur_kwh": 0.07, "accise_eur_kwh": 0.02998, "price_ht_eur_kwh": 0.12253, "price_ttc_eur_kwh": 0.14704}, {"timestamp": "2026-03-03T11:30:00+01:00", "spot_price": 23.19, "spot_price_eur_kwh": 0.02319, "turpe_eur_kwh": 0.07, "accise_eur_kwh": 0.02998, "price_ht_eur_kwh": 0.12317, "price_ttc_eur_kwh": 0.1478}, {"timestamp": "2026-03-03T11:45:00+01:00", "spot_price": 4.06, "spot_price_eur_kwh": 0.00406, "turpe_eur_kwh": 0.07, "accise_eur_kwh": 0.02998, "price_ht_eur_kwh": 0.10404, "price_ttc_eur_kwh": 0.12485}, {"timestamp": "2026-03-03T12:00:00+01:00", "spot_price": 40.08, "spot_price_eur_kwh": 0.04008, "turpe_eur_kwh": 0.07, "accise_eur_kwh": 0.02998, "price_ht_eur_kwh": 0.14006, "price_ttc_eur_kwh": 0.16807}, {"timestamp": "2026-03-03T12:15:00+01:00", "spot_price": 27.98, "spot_price_eur_kwh": 0.02798, "turpe_eur_kwh": 0.07, "accise_eur_kwh": 0.02998, "price_ht_eur_kwh": 0.12796, "price_ttc_eur_kwh": 0.15355}, {"timestamp": "2026-03-03T12:30:00+01:00", "spot_price": 24.46, "spot_price_eur_kwh": 0.02446, "turpe_eur_kwh": 0.07, "accise_eur_kwh": 0.02998, "price_ht_eur_kwh": 0.12444, "price_ttc_eur_kwh": 0.14933}, {"timestamp": "2026-03-03T12:45:00+01:00", "spot_price": 1.2, "spot_price_eur_kwh": 0.0012, "turpe_eur_kwh": 0.07, "accise_eur_kwh": 0.02998, "price_ht_eur_kwh": 0.10118, "price_ttc_eur_kwh": 0.12142}, {"timestamp": "2026-03-03T13:00:00+01:00", "spot_price": 12, "spot_price_eur_kwh": 0.012, "turpe_eur_kwh": 0.07, "accise_eur_kwh": 0.02998, "price_ht_eur_kwh": 0.11198, "price_ttc_eur_kwh": 0.13438}, {"timestamp": "2026-03-03T13:15:00+01:00", "spot_price": 1.43, "spot_price_eur_kwh": 0.00143, "turpe_eur_kwh": 0.07, "accise_eur_kwh": 0.02998, "price_ht_eur_kwh": 0.10141, "price_ttc_eur_kwh": 0.12169}, {"timestamp": "2026-03-03T13:30:00+01:00", "spot_price": 0.91, "spot_price_eur_kwh": 0.00091, "turpe_eur_kwh": 0.07, "accise_eur_kwh": 0.02998, "price_ht_eur_kwh": 0.10089, "price_ttc_eur_kwh": 0.12107}, {"timestamp": "2026-03-03T13:45:00+01:00", "spot_price": 0.91, "spot_price_eur_kwh": 0.00091, "turpe_eur_kwh": 0.07, "accise_eur_kwh": 0.02998, "price_ht_eur_kwh": 0.10089, "price_ttc_eur_kwh": 0.12107}, {"timestamp": "2026-03-03T14:00:00+01:00", "spot_price": 7.46, "spot_price_eur_kwh": 0.00746, "turpe_eur_kwh": 0.07, "accise_eur_kwh": 0.02998, "price_ht_eur_kwh": 0.10744, "price_ttc_eur_kwh": 0.12893}, {"timestamp": "2026-03-03T14:15:00+01:00", "spot_price": 15.61, "spot_price_eur_kwh": 0.01561, "turpe_eur_kwh": 0.07, "accise_eur_kwh": 0.02998, "price_ht_eur_kwh": 0.11559, "price_ttc_eur_kwh": 0.13871}, {"timestamp": "2026-03-03T14:30:00+01:00", "spot_price": 5.83, "spot_price_eur_kwh": 0.00583, "turpe_eur_kwh": 0.07, "accise_eur_kwh": 0.02998, "price_ht_eur_kwh": 0.10581, "price_ttc_eur_kwh": 0.12697}, {"timestamp": "2026-03-03T14:45:00+01:00", "spot_price": 11.13, "spot_price_eur_kwh": 0.01113, "turpe_eur_kwh": 0.07, "accise_eur_kwh": 0.02998, "price_ht_eur_kwh": 0.11111, "price_ttc_eur_kwh": 0.13333}, {"timestamp": "2026-03-03T15:00:00+01:00", "spot_price": 4.38, "spot_price_eur_kwh": 0.00438, "turpe_eur_kwh": 0.07, "accise_eur_kwh": 0.02998, "price_ht_eur_kwh": 0.10436, "price_ttc_eur_kwh": 0.12523}, {"timestamp": "2026-03-03T15:15:00+01:00", "spot_price": 28.55, "spot_price_eur_kwh": 0.02855, "turpe_eur_kwh": 0.07, "accise_eur_kwh": 0.02998, "price_ht_eur_kwh": 0.12853, "price_ttc_eur_kwh": 0.15424}, {"timestamp": "2026-03-03T15:30:00+01:00", "spot_price": 27.3, "spot_price_eur_kwh": 0.0273, "turpe_eur_kwh": 0.07, "accise_eur_kwh": 0.02998, "price_ht_eur_kwh": 0.12728, "price_ttc_eur_kwh": 0.15274}, {"timestamp": "2026-03-03T15:45:00+01:00", "spot_price": 47.96, "spot_price_eur_kwh": 0.04796, "turpe_eur_kwh": 0.07, "accise_eur_kwh": 0.02998, "price_ht_eur_kwh": 0.14794, "price_ttc_eur_kwh": 0.17753}, {"timestamp": "2026-03-03T16:00:00+01:00", "spot_price": 20.96, "spot_price_eur_kwh": 0.02096, "turpe_eur_kwh": 0.07, "accise_eur_kwh": 0.02998, "price_ht_eur_kwh": 0.12094, "price_ttc_eur_kwh": 0.14513}, {"timestamp": "2026-03-03T16:15:00+01:00", "spot_price": 50.01, "spot_price_eur_kwh": 0.05001, "turpe_eur_kwh": 0.07, "accise_eur_kwh": 0.02998, "price_ht_eur_kwh": 0.14999, "price_ttc_eur_kwh": 0.17999}, {"timestamp": "2026-03-03T16:30:00+01:00", "spot_price": 38.4, "spot_price_eur_kwh": 0.0384, "turpe_eur_kwh": 0.07, "accise_eur_kwh": 0.02998, "price_ht_eur_kwh": 0.13838, "price_ttc_eur_kwh": 0.16606}, {"timestamp": "2026-03-03T16:45:00+01:00", "spot_price": 38.23, "spot_price_eur_kwh": 0.03823, "turpe_eur_kwh": 0.07, "accise_eur_kwh": 0.02998, "price_ht_eur_kwh": 0.13821, "price_ttc_eur_kwh": 0.16585}, {"timestamp": "2026-03-03T17:00:00+01:00", "spot_price": 29.32, "spot_price_eur_kwh": 0.02932, "turpe_eur_kwh": 0.07, "accise_eur_kwh": 0.02998, "price_ht_eur_kwh": 0.1293, "price_ttc_eur_kwh": 0.15516}, {"timestamp": "2026-03-03T17:15:00+01:00", "spot_price": 50.47, "spot_price_eur_kwh": 0.05047, "turpe_eur_kwh": 0.07, "accise_eur_kwh": 0.02998, "price_ht_eur_kwh": 0.15045, "price_ttc_eur_kwh": 0.18054}, {"timestamp": "2026-03-03T17:30:00+01:00", "spot_price": 49.23, "spot_price_eur_kwh": 0.04923, "turpe_eur_kwh": 0.07, "accise_eur_kwh": 0.02998, "price_ht_eur_kwh": 0.14921, "price_ttc_eur_kwh": 0.17905}, {"timestamp": "2026-03-03T17:45:00+01:00", "spot_price": 71.01, "spot_price_eur_kwh": 0.07101, "turpe_eur_kwh": 0.07, "accise_eur_kwh": 0.02998, "price_ht_eur_kwh": 0.17099, "price_ttc_eur_kwh": 0.20519}, {"timestamp": "2026-03-03T18:00:00+01:00", "spot_price": 31.31, "spot_price_eur_kwh": 0.03131, "turpe_eur_kwh": 0.07, "accise_eur_kwh": 0.02998, "price_ht_eur_kwh": 0.13129, "price_ttc_eur_kwh": 0.15755}, {"timestamp": "2026-03-03T18:15:00+01:00", "spot_price": 57.04, "spot_price_eur_kwh": 0.05704, "turpe_eur_kwh": 0.07, "accise_eur_kwh": 0.02998, "price_ht_eur_kwh": 0.15702, "price_ttc_eur_kwh": 0.18842}, {"timestamp": "2026-03-03T18:30:00+01:00", "spot_price": 96.96, "spot_price_eur_kwh": 0.09696, "turpe_eur_kwh": 0.07, "accise_eur_kwh": 0.02998, "price_ht_eur_kwh": 0.19694, "price_ttc_eur_kwh": 0.23633}, {"timestamp": "2026-03-03T18:45:00+01:00", "spot_price": 193.24, "spot_price_eur_kwh": 0.19324, "turpe_eur_kwh": 0.07, "accise_eur_kwh": 0.02998, "price_ht_eur_kwh": 0.29322, "price_ttc_eur_kwh": 0.35186}, {"timestamp": "2026-03-03T19:00:00+01:00", "spot_price": 188.14, "spot_price_eur_kwh": 0.18814, "turpe_eur_kwh": 0.07, "accise_eur_kwh": 0.02998, "price_ht_eur_kwh": 0.28812, "price_ttc_eur_kwh": 0.34574}, {"timestamp": "2026-03-03T19:15:00+01:00", "spot_price": 180.64, "spot_price_eur_kwh": 0.18064, "turpe_eur_kwh": 0.07, "accise_eur_kwh": 0.02998, "price_ht_eur_kwh": 0.28062, "price_ttc_eur_kwh": 0.33674}, {"timestamp": "2026-03-03T19:30:00+01:00", "spot_price": 158.31, "spot_price_eur_kwh": 0.15831, "turpe_eur_kwh": 0.07, "accise_eur_kwh": 0.02998, "price_ht_eur_kwh": 0.25829, "price_ttc_eur_kwh": 0.30995}, {"timestamp": "2026-03-03T19:45:00+01:00", "spot_price": 107.41, "spot_price_eur_kwh": 0.10741, "turpe_eur_kwh": 0.07, "accise_eur_kwh": 0.02998, "price_ht_eur_kwh": 0.20739, "price_ttc_eur_kwh": 0.24887}, {"timestamp": "2026-03-03T20:00:00+01:00", "spot_price": 106.6, "spot_price_eur_kwh": 0.1066, "turpe_eur_kwh": 0.07, "accise_eur_kwh": 0.02998, "price_ht_eur_kwh": 0.20658, "price_ttc_eur_kwh": 0.2479}, {"timestamp": "2026-03-03T20:15:00+01:00", "spot_price": 100.28, "spot_price_eur_kwh": 0.10028, "turpe_eur_kwh": 0.07, "accise_eur_kwh": 0.02998, "price_ht_eur_kwh": 0.20026, "price_ttc_eur_kwh": 0.24031}, {"timestamp": "2026-03-03T20:30:00+01:00", "spot_price": 87.24, "spot_price_eur_kwh": 0.08724, "turpe_eur_kwh": 0.07, "accise_eur_kwh": 0.02998, "price_ht_eur_kwh": 0.18722, "price_ttc_eur_kwh": 0.22466}, {"timestamp": "2026-03-03T20:45:00+01:00", "spot_price": 79.27, "spot_price_eur_kwh": 0.07927, "turpe_eur_kwh": 0.07, "accise_eur_kwh": 0.02998, "price_ht_eur_kwh": 0.17925, "price_ttc_eur_kwh": 0.2151}, {"timestamp": "2026-03-03T21:00:00+01:00", "spot_price": 69.57, "spot_price_eur_kwh": 0.06957, "turpe_eur_kwh": 0.07, "accise_eur_kwh": 0.02998, "price_ht_eur_kwh": 0.16955, "price_ttc_eur_kwh": 0.20346}, {"timestamp": "2026-03-03T21:15:00+01:00", "spot_price": 67.73, "spot_price_eur_kwh": 0.06773, "turpe_eur_kwh": 0.07, "accise_eur_kwh": 0.02998, "price_ht_eur_kwh": 0.16771, "price_ttc_eur_kwh": 0.20125}, {"timestamp": "2026-03-03T21:30:00+01:00", "spot_price": 65, "spot_price_eur_kwh": 0.065, "turpe_eur_kwh": 0.07, "accise_eur_kwh": 0.02998, "price_ht_eur_kwh": 0.16498, "price_ttc_eur_kwh": 0.19798}, {"timestamp": "2026-03-03T21:45:00+01:00", "spot_price": 47.02, "spot_price_eur_kwh": 0.04702, "turpe_eur_kwh": 0.07, "accise_eur_kwh": 0.02998, "price_ht_eur_kwh": 0.147, "price_ttc_eur_kwh": 0.1764}, {"timestamp": "2026-03-03T22:00:00+01:00", "spot_price": 63.58, "spot_price_eur_kwh": 0.06358, "turpe_eur_kwh": 0.07, "accise_eur_kwh": 0.02998, "price_ht_eur_kwh": 0.16356, "price_ttc_eur_kwh": 0.19627}, {"timestamp": "2026-03-03T22:15:00+01:00", "spot_price": 50.24, "spot_price_eur_kwh": 0.05024, "turpe_eur_kwh": 0.07, "accise_eur_kwh": 0.02998, "price_ht_eur_kwh": 0.15022, "price_ttc_eur_kwh": 0.18026}, {"timestamp": "2026-03-03T22:30:00+01:00", "spot_price": 68.51, "spot_price_eur_kwh": 0.06851, "turpe_eur_kwh": 0.07, "accise_eur_kwh": 0.02998, "price_ht_eur_kwh": 0.16849, "price_ttc_eur_kwh": 0.20219}, {"timestamp": "2026-03-03T22:45:00+01:00", "spot_price": 41.64, "spot_price_eur_kwh": 0.04164, "turpe_eur_kwh": 0.07, "accise_eur_kwh": 0.02998, "price_ht_eur_kwh": 0.14162, "price_ttc_eur_kwh": 0.16994}, {"timestamp": "2026-03-03T23:00:00+01:00", "spot_price": 52.57, "spot_price_eur_kwh": 0.05257, "turpe_eur_kwh": 0.0373, "accise_eur_kwh": 0.02998, "price_ht_eur_kwh": 0.11985, "price_ttc_eur_kwh": 0.14382}, {"timestamp": "2026-03-03T23:15:00+01:00", "spot_price": 35.02, "spot_price_eur_kwh": 0.03502, "turpe_eur_kwh": 0.0373, "accise_eur_kwh": 0.02998, "price_ht_eur_kwh": 0.1023, "price_ttc_eur_kwh": 0.12276}, {"timestamp": "2026-03-03T23:30:00+01:00", "spot_price": 64.44, "spot_price_eur_kwh": 0.06444, "turpe_eur_kwh": 0.0373, "accise_eur_kwh": 0.02998, "price_ht_eur_kwh": 0.13172, "price_ttc_eur_kwh": 0.15806}, {"timestamp": "2026-03-03T23:45:00+01:00", "spot_price": 35, "spot_price_eur_kwh": 0.035, "turpe_eur_kwh": 0.0373, "accise_eur_kwh": 0.02998, "price_ht_eur_kwh": 0.10228, "price_ttc_eur_kwh": 0.12274}], "pricing_metadata": {"enabled": true, "segment": "C5", "turpe_option": "MU4", "profil": "particulier", "display": "TTC", "tva_rate": 0.2, "accise_eur_kwh": 0.02998, "turpe_source": "table interne Sobry C5 (c\u20ac/kWh \u2192 \u20ac/kWh)", "formula_ht": "spot_price_eur_kwh + turpe_eur_kwh + accise_eur_kwh", "formula_ttc": "price_ht_eur_kwh \u00d7 (1 + TVA 20%)", "units": {"spot_price": "\u20ac/MWh", "all_other_prices": "\u20ac/kWh"}}}