{"success": true, "date": "2026-03-02", "timezone": "Europe/Paris (CET)", "count": 96, "statistics": {"min": 0, "max": 150.73, "average": 29.3, "median": 18.64}, "prices": [{"timestamp": "2026-03-02T00:00:00+01:00", "spot_price": 23, "spot_price_eur_kwh": 0.023, "turpe_eur_kwh": 0.0125, "accise_eur_kwh": 0.02579, "price_ht_eur_kwh": 0.06129, "price_ttc_eur_kwh": 0.07355}, {"timestamp": "2026-03-02T00:15:00+01:00", "spot_price": 20.01, "spot_price_eur_kwh": 0.02001, "turpe_eur_kwh": 0.0125, "accise_eur_kwh": 0.02579, "price_ht_eur_kwh": 0.0583, "price_ttc_eur_kwh": 0.06996}, {"timestamp": "2026-03-02T00:30:00+01:00", "spot_price": 14, "spot_price_eur_kwh": 0.014, "turpe_eur_kwh": 0.0125, "accise_eur_kwh": 0.02579, "price_ht_eur_kwh": 0.05229, "price_ttc_eur_kwh": 0.06275}, {"timestamp": "2026-03-02T00:45:00+01:00", "spot_price": 6.5, "spot_price_eur_kwh": 0.0065, "turpe_eur_kwh": 0.0125, "accise_eur_kwh": 0.02579, "price_ht_eur_kwh": 0.04479, "price_ttc_eur_kwh": 0.05375}, {"timestamp": "2026-03-02T01:00:00+01:00", "spot_price": 14, "spot_price_eur_kwh": 0.014, "turpe_eur_kwh": 0.0125, "accise_eur_kwh": 0.02579, "price_ht_eur_kwh": 0.05229, "price_ttc_eur_kwh": 0.06275}, {"timestamp": "2026-03-02T01:15:00+01:00", "spot_price": 7.01, "spot_price_eur_kwh": 0.00701, "turpe_eur_kwh": 0.0125, "accise_eur_kwh": 0.02579, "price_ht_eur_kwh": 0.0453, "price_ttc_eur_kwh": 0.05436}, {"timestamp": "2026-03-02T01:30:00+01:00", "spot_price": 8.49, "spot_price_eur_kwh": 0.00849, "turpe_eur_kwh": 0.0125, "accise_eur_kwh": 0.02579, "price_ht_eur_kwh": 0.04678, "price_ttc_eur_kwh": 0.05614}, {"timestamp": "2026-03-02T01:45:00+01:00", "spot_price": 6, "spot_price_eur_kwh": 0.006, "turpe_eur_kwh": 0.0125, "accise_eur_kwh": 0.02579, "price_ht_eur_kwh": 0.04429, "price_ttc_eur_kwh": 0.05315}, {"timestamp": "2026-03-02T02:00:00+01:00", "spot_price": 18.36, "spot_price_eur_kwh": 0.01836, "turpe_eur_kwh": 0.0125, "accise_eur_kwh": 0.02579, "price_ht_eur_kwh": 0.05665, "price_ttc_eur_kwh": 0.06798}, {"timestamp": "2026-03-02T02:15:00+01:00", "spot_price": 8.89, "spot_price_eur_kwh": 0.00889, "turpe_eur_kwh": 0.0125, "accise_eur_kwh": 0.02579, "price_ht_eur_kwh": 0.04718, "price_ttc_eur_kwh": 0.05662}, {"timestamp": "2026-03-02T02:30:00+01:00", "spot_price": 7.03, "spot_price_eur_kwh": 0.00703, "turpe_eur_kwh": 0.0125, "accise_eur_kwh": 0.02579, "price_ht_eur_kwh": 0.04532, "price_ttc_eur_kwh": 0.05438}, {"timestamp": "2026-03-02T02:45:00+01:00", "spot_price": 5, "spot_price_eur_kwh": 0.005, "turpe_eur_kwh": 0.0125, "accise_eur_kwh": 0.02579, "price_ht_eur_kwh": 0.04329, "price_ttc_eur_kwh": 0.05195}, {"timestamp": "2026-03-02T03:00:00+01:00", "spot_price": 9.34, "spot_price_eur_kwh": 0.00934, "turpe_eur_kwh": 0.0125, "accise_eur_kwh": 0.02579, "price_ht_eur_kwh": 0.04763, "price_ttc_eur_kwh": 0.05716}, {"timestamp": "2026-03-02T03:15:00+01:00", "spot_price": 7.92, "spot_price_eur_kwh": 0.00792, "turpe_eur_kwh": 0.0125, "accise_eur_kwh": 0.02579, "price_ht_eur_kwh": 0.04621, "price_ttc_eur_kwh": 0.05545}, {"timestamp": "2026-03-02T03:30:00+01:00", "spot_price": 6.64, "spot_price_eur_kwh": 0.00664, "turpe_eur_kwh": 0.0125, "accise_eur_kwh": 0.02579, "price_ht_eur_kwh": 0.04493, "price_ttc_eur_kwh": 0.05392}, {"timestamp": "2026-03-02T03:45:00+01:00", "spot_price": 4.5, "spot_price_eur_kwh": 0.0045, "turpe_eur_kwh": 0.0125, "accise_eur_kwh": 0.02579, "price_ht_eur_kwh": 0.04279, "price_ttc_eur_kwh": 0.05135}, {"timestamp": "2026-03-02T04:00:00+01:00", "spot_price": 8.6, "spot_price_eur_kwh": 0.0086, "turpe_eur_kwh": 0.0125, "accise_eur_kwh": 0.02579, "price_ht_eur_kwh": 0.04689, "price_ttc_eur_kwh": 0.05627}, {"timestamp": "2026-03-02T04:15:00+01:00", "spot_price": 5.11, "spot_price_eur_kwh": 0.00511, "turpe_eur_kwh": 0.0125, "accise_eur_kwh": 0.02579, "price_ht_eur_kwh": 0.0434, "price_ttc_eur_kwh": 0.05208}, {"timestamp": "2026-03-02T04:30:00+01:00", "spot_price": 8.17, "spot_price_eur_kwh": 0.00817, "turpe_eur_kwh": 0.0125, "accise_eur_kwh": 0.02579, "price_ht_eur_kwh": 0.04646, "price_ttc_eur_kwh": 0.05575}, {"timestamp": "2026-03-02T04:45:00+01:00", "spot_price": 4.26, "spot_price_eur_kwh": 0.00426, "turpe_eur_kwh": 0.0125, "accise_eur_kwh": 0.02579, "price_ht_eur_kwh": 0.04255, "price_ttc_eur_kwh": 0.05106}, {"timestamp": "2026-03-02T05:00:00+01:00", "spot_price": 6.49, "spot_price_eur_kwh": 0.00649, "turpe_eur_kwh": 0.0125, "accise_eur_kwh": 0.02579, "price_ht_eur_kwh": 0.04478, "price_ttc_eur_kwh": 0.05374}, {"timestamp": "2026-03-02T05:15:00+01:00", "spot_price": 6, "spot_price_eur_kwh": 0.006, "turpe_eur_kwh": 0.0125, "accise_eur_kwh": 0.02579, "price_ht_eur_kwh": 0.04429, "price_ttc_eur_kwh": 0.05315}, {"timestamp": "2026-03-02T05:30:00+01:00", "spot_price": 7.96, "spot_price_eur_kwh": 0.00796, "turpe_eur_kwh": 0.0125, "accise_eur_kwh": 0.02579, "price_ht_eur_kwh": 0.04625, "price_ttc_eur_kwh": 0.0555}, {"timestamp": "2026-03-02T05:45:00+01:00", "spot_price": 17.53, "spot_price_eur_kwh": 0.01753, "turpe_eur_kwh": 0.0125, "accise_eur_kwh": 0.02579, "price_ht_eur_kwh": 0.05582, "price_ttc_eur_kwh": 0.06698}, {"timestamp": "2026-03-02T06:00:00+01:00", "spot_price": 19.82, "spot_price_eur_kwh": 0.01982, "turpe_eur_kwh": 0.0125, "accise_eur_kwh": 0.02579, "price_ht_eur_kwh": 0.05811, "price_ttc_eur_kwh": 0.06973}, {"timestamp": "2026-03-02T06:15:00+01:00", "spot_price": 20.06, "spot_price_eur_kwh": 0.02006, "turpe_eur_kwh": 0.0125, "accise_eur_kwh": 0.02579, "price_ht_eur_kwh": 0.05835, "price_ttc_eur_kwh": 0.07002}, {"timestamp": "2026-03-02T06:30:00+01:00", "spot_price": 20.3, "spot_price_eur_kwh": 0.0203, "turpe_eur_kwh": 0.0125, "accise_eur_kwh": 0.02579, "price_ht_eur_kwh": 0.05859, "price_ttc_eur_kwh": 0.07031}, {"timestamp": "2026-03-02T06:45:00+01:00", "spot_price": 27.8, "spot_price_eur_kwh": 0.0278, "turpe_eur_kwh": 0.0125, "accise_eur_kwh": 0.02579, "price_ht_eur_kwh": 0.06609, "price_ttc_eur_kwh": 0.07931}, {"timestamp": "2026-03-02T07:00:00+01:00", "spot_price": 22.36, "spot_price_eur_kwh": 0.02236, "turpe_eur_kwh": 0.0125, "accise_eur_kwh": 0.02579, "price_ht_eur_kwh": 0.06065, "price_ttc_eur_kwh": 0.07278}, {"timestamp": "2026-03-02T07:15:00+01:00", "spot_price": 27.19, "spot_price_eur_kwh": 0.02719, "turpe_eur_kwh": 0.0125, "accise_eur_kwh": 0.02579, "price_ht_eur_kwh": 0.06548, "price_ttc_eur_kwh": 0.07858}, {"timestamp": "2026-03-02T07:30:00+01:00", "spot_price": 35.25, "spot_price_eur_kwh": 0.03525, "turpe_eur_kwh": 0.0125, "accise_eur_kwh": 0.02579, "price_ht_eur_kwh": 0.07354, "price_ttc_eur_kwh": 0.08825}, {"timestamp": "2026-03-02T07:45:00+01:00", "spot_price": 50.49, "spot_price_eur_kwh": 0.05049, "turpe_eur_kwh": 0.0125, "accise_eur_kwh": 0.02579, "price_ht_eur_kwh": 0.08878, "price_ttc_eur_kwh": 0.10654}, {"timestamp": "2026-03-02T08:00:00+01:00", "spot_price": 76.36, "spot_price_eur_kwh": 0.07636, "turpe_eur_kwh": 0.0125, "accise_eur_kwh": 0.02579, "price_ht_eur_kwh": 0.11465, "price_ttc_eur_kwh": 0.13758}, {"timestamp": "2026-03-02T08:15:00+01:00", "spot_price": 46.12, "spot_price_eur_kwh": 0.04612, "turpe_eur_kwh": 0.0125, "accise_eur_kwh": 0.02579, "price_ht_eur_kwh": 0.08441, "price_ttc_eur_kwh": 0.10129}, {"timestamp": "2026-03-02T08:30:00+01:00", "spot_price": 31.17, "spot_price_eur_kwh": 0.03117, "turpe_eur_kwh": 0.0125, "accise_eur_kwh": 0.02579, "price_ht_eur_kwh": 0.06946, "price_ttc_eur_kwh": 0.08335}, {"timestamp": "2026-03-02T08:45:00+01:00", "spot_price": 14.35, "spot_price_eur_kwh": 0.01435, "turpe_eur_kwh": 0.0125, "accise_eur_kwh": 0.02579, "price_ht_eur_kwh": 0.05264, "price_ttc_eur_kwh": 0.06317}, {"timestamp": "2026-03-02T09:00:00+01:00", "spot_price": 30.87, "spot_price_eur_kwh": 0.03087, "turpe_eur_kwh": 0.0125, "accise_eur_kwh": 0.02579, "price_ht_eur_kwh": 0.06916, "price_ttc_eur_kwh": 0.08299}, {"timestamp": "2026-03-02T09:15:00+01:00", "spot_price": 29.07, "spot_price_eur_kwh": 0.02907, "turpe_eur_kwh": 0.0125, "accise_eur_kwh": 0.02579, "price_ht_eur_kwh": 0.06736, "price_ttc_eur_kwh": 0.08083}, {"timestamp": "2026-03-02T09:30:00+01:00", "spot_price": 25.49, "spot_price_eur_kwh": 0.02549, "turpe_eur_kwh": 0.0125, "accise_eur_kwh": 0.02579, "price_ht_eur_kwh": 0.06378, "price_ttc_eur_kwh": 0.07654}, {"timestamp": "2026-03-02T09:45:00+01:00", "spot_price": 14.57, "spot_price_eur_kwh": 0.01457, "turpe_eur_kwh": 0.0125, "accise_eur_kwh": 0.02579, "price_ht_eur_kwh": 0.05286, "price_ttc_eur_kwh": 0.06343}, {"timestamp": "2026-03-02T10:00:00+01:00", "spot_price": 26.23, "spot_price_eur_kwh": 0.02623, "turpe_eur_kwh": 0.0125, "accise_eur_kwh": 0.02579, "price_ht_eur_kwh": 0.06452, "price_ttc_eur_kwh": 0.07742}, {"timestamp": "2026-03-02T10:15:00+01:00", "spot_price": 2.5, "spot_price_eur_kwh": 0.0025, "turpe_eur_kwh": 0.0125, "accise_eur_kwh": 0.02579, "price_ht_eur_kwh": 0.04079, "price_ttc_eur_kwh": 0.04895}, {"timestamp": "2026-03-02T10:30:00+01:00", "spot_price": 1.85, "spot_price_eur_kwh": 0.00185, "turpe_eur_kwh": 0.0125, "accise_eur_kwh": 0.02579, "price_ht_eur_kwh": 0.04014, "price_ttc_eur_kwh": 0.04817}, {"timestamp": "2026-03-02T10:45:00+01:00", "spot_price": 0.91, "spot_price_eur_kwh": 0.00091, "turpe_eur_kwh": 0.0125, "accise_eur_kwh": 0.02579, "price_ht_eur_kwh": 0.0392, "price_ttc_eur_kwh": 0.04704}, {"timestamp": "2026-03-02T11:00:00+01:00", "spot_price": 25.06, "spot_price_eur_kwh": 0.02506, "turpe_eur_kwh": 0.0125, "accise_eur_kwh": 0.02579, "price_ht_eur_kwh": 0.06335, "price_ttc_eur_kwh": 0.07602}, {"timestamp": "2026-03-02T11:15:00+01:00", "spot_price": 0.06, "spot_price_eur_kwh": 6e-05, "turpe_eur_kwh": 0.0125, "accise_eur_kwh": 0.02579, "price_ht_eur_kwh": 0.03835, "price_ttc_eur_kwh": 0.04602}, {"timestamp": "2026-03-02T11:30:00+01:00", "spot_price": 0, "spot_price_eur_kwh": 0, "turpe_eur_kwh": 0.0125, "accise_eur_kwh": 0.02579, "price_ht_eur_kwh": 0.03829, "price_ttc_eur_kwh": 0.04595}, {"timestamp": "2026-03-02T11:45:00+01:00", "spot_price": 0, "spot_price_eur_kwh": 0, "turpe_eur_kwh": 0.0125, "accise_eur_kwh": 0.02579, "price_ht_eur_kwh": 0.03829, "price_ttc_eur_kwh": 0.04595}, {"timestamp": "2026-03-02T12:00:00+01:00", "spot_price": 0, "spot_price_eur_kwh": 0, "turpe_eur_kwh": 0.0125, "accise_eur_kwh": 0.02579, "price_ht_eur_kwh": 0.03829, "price_ttc_eur_kwh": 0.04595}, {"timestamp": "2026-03-02T12:15:00+01:00", "spot_price": 0.5, "spot_price_eur_kwh": 0.0005, "turpe_eur_kwh": 0.0125, "accise_eur_kwh": 0.02579, "price_ht_eur_kwh": 0.03879, "price_ttc_eur_kwh": 0.04655}, {"timestamp": "2026-03-02T12:30:00+01:00", "spot_price": 18.64, "spot_price_eur_kwh": 0.01864, "turpe_eur_kwh": 0.0125, "accise_eur_kwh": 0.02579, "price_ht_eur_kwh": 0.05693, "price_ttc_eur_kwh": 0.06832}, {"timestamp": "2026-03-02T12:45:00+01:00", "spot_price": 0.06, "spot_price_eur_kwh": 6e-05, "turpe_eur_kwh": 0.0125, "accise_eur_kwh": 0.02579, "price_ht_eur_kwh": 0.03835, "price_ttc_eur_kwh": 0.04602}, {"timestamp": "2026-03-02T13:00:00+01:00", "spot_price": 0, "spot_price_eur_kwh": 0, "turpe_eur_kwh": 0.0125, "accise_eur_kwh": 0.02579, "price_ht_eur_kwh": 0.03829, "price_ttc_eur_kwh": 0.04595}, {"timestamp": "2026-03-02T13:15:00+01:00", "spot_price": 0, "spot_price_eur_kwh": 0, "turpe_eur_kwh": 0.0125, "accise_eur_kwh": 0.02579, "price_ht_eur_kwh": 0.03829, "price_ttc_eur_kwh": 0.04595}, {"timestamp": "2026-03-02T13:30:00+01:00", "spot_price": 0, "spot_price_eur_kwh": 0, "turpe_eur_kwh": 0.0125, "accise_eur_kwh": 0.02579, "price_ht_eur_kwh": 0.03829, "price_ttc_eur_kwh": 0.04595}, {"timestamp": "2026-03-02T13:45:00+01:00", "spot_price": 0, "spot_price_eur_kwh": 0, "turpe_eur_kwh": 0.0125, "accise_eur_kwh": 0.02579, "price_ht_eur_kwh": 0.03829, "price_ttc_eur_kwh": 0.04595}, {"timestamp": "2026-03-02T14:00:00+01:00", "spot_price": 0, "spot_price_eur_kwh": 0, "turpe_eur_kwh": 0.0125, "accise_eur_kwh": 0.02579, "price_ht_eur_kwh": 0.03829, "price_ttc_eur_kwh": 0.04595}, {"timestamp": "2026-03-02T14:15:00+01:00", "spot_price": 0, "spot_price_eur_kwh": 0, "turpe_eur_kwh": 0.0125, "accise_eur_kwh": 0.02579, "price_ht_eur_kwh": 0.03829, "price_ttc_eur_kwh": 0.04595}, {"timestamp": "2026-03-02T14:30:00+01:00", "spot_price": 9.41, "spot_price_eur_kwh": 0.00941, "turpe_eur_kwh": 0.0125, "accise_eur_kwh": 0.02579, "price_ht_eur_kwh": 0.0477, "price_ttc_eur_kwh": 0.05724}, {"timestamp": "2026-03-02T14:45:00+01:00", "spot_price": 8.29, "spot_price_eur_kwh": 0.00829, "turpe_eur_kwh": 0.0125, "accise_eur_kwh": 0.02579, "price_ht_eur_kwh": 0.04658, "price_ttc_eur_kwh": 0.0559}, {"timestamp": "2026-03-02T15:00:00+01:00", "spot_price": 0.03, "spot_price_eur_kwh": 3e-05, "turpe_eur_kwh": 0.0125, "accise_eur_kwh": 0.02579, "price_ht_eur_kwh": 0.03832, "price_ttc_eur_kwh": 0.04598}, {"timestamp": "2026-03-02T15:15:00+01:00", "spot_price": 0.6, "spot_price_eur_kwh": 0.0006, "turpe_eur_kwh": 0.0125, "accise_eur_kwh": 0.02579, "price_ht_eur_kwh": 0.03889, "price_ttc_eur_kwh": 0.04667}, {"timestamp": "2026-03-02T15:30:00+01:00", "spot_price": 7.07, "spot_price_eur_kwh": 0.00707, "turpe_eur_kwh": 0.0125, "accise_eur_kwh": 0.02579, "price_ht_eur_kwh": 0.04536, "price_ttc_eur_kwh": 0.05443}, {"timestamp": "2026-03-02T15:45:00+01:00", "spot_price": 0.91, "spot_price_eur_kwh": 0.00091, "turpe_eur_kwh": 0.0125, "accise_eur_kwh": 0.02579, "price_ht_eur_kwh": 0.0392, "price_ttc_eur_kwh": 0.04704}, {"timestamp": "2026-03-02T16:00:00+01:00", "spot_price": 7.71, "spot_price_eur_kwh": 0.00771, "turpe_eur_kwh": 0.0125, "accise_eur_kwh": 0.02579, "price_ht_eur_kwh": 0.046, "price_ttc_eur_kwh": 0.0552}, {"timestamp": "2026-03-02T16:15:00+01:00", "spot_price": 27.27, "spot_price_eur_kwh": 0.02727, "turpe_eur_kwh": 0.0125, "accise_eur_kwh": 0.02579, "price_ht_eur_kwh": 0.06556, "price_ttc_eur_kwh": 0.07867}, {"timestamp": "2026-03-02T16:30:00+01:00", "spot_price": 23.95, "spot_price_eur_kwh": 0.02395, "turpe_eur_kwh": 0.0125, "accise_eur_kwh": 0.02579, "price_ht_eur_kwh": 0.06224, "price_ttc_eur_kwh": 0.07469}, {"timestamp": "2026-03-02T16:45:00+01:00", "spot_price": 29.07, "spot_price_eur_kwh": 0.02907, "turpe_eur_kwh": 0.0125, "accise_eur_kwh": 0.02579, "price_ht_eur_kwh": 0.06736, "price_ttc_eur_kwh": 0.08083}, {"timestamp": "2026-03-02T17:00:00+01:00", "spot_price": 16.46, "spot_price_eur_kwh": 0.01646, "turpe_eur_kwh": 0.0125, "accise_eur_kwh": 0.02579, "price_ht_eur_kwh": 0.05475, "price_ttc_eur_kwh": 0.0657}, {"timestamp": "2026-03-02T17:15:00+01:00", "spot_price": 16.24, "spot_price_eur_kwh": 0.01624, "turpe_eur_kwh": 0.0125, "accise_eur_kwh": 0.02579, "price_ht_eur_kwh": 0.05453, "price_ttc_eur_kwh": 0.06544}, {"timestamp": "2026-03-02T17:30:00+01:00", "spot_price": 46.27, "spot_price_eur_kwh": 0.04627, "turpe_eur_kwh": 0.0125, "accise_eur_kwh": 0.02579, "price_ht_eur_kwh": 0.08456, "price_ttc_eur_kwh": 0.10147}, {"timestamp": "2026-03-02T17:45:00+01:00", "spot_price": 75.89, "spot_price_eur_kwh": 0.07589, "turpe_eur_kwh": 0.0125, "accise_eur_kwh": 0.02579, "price_ht_eur_kwh": 0.11418, "price_ttc_eur_kwh": 0.13702}, {"timestamp": "2026-03-02T18:00:00+01:00", "spot_price": 61.17, "spot_price_eur_kwh": 0.06117, "turpe_eur_kwh": 0.0125, "accise_eur_kwh": 0.02579, "price_ht_eur_kwh": 0.09946, "price_ttc_eur_kwh": 0.11935}, {"timestamp": "2026-03-02T18:15:00+01:00", "spot_price": 72.86, "spot_price_eur_kwh": 0.07286, "turpe_eur_kwh": 0.0125, "accise_eur_kwh": 0.02579, "price_ht_eur_kwh": 0.11115, "price_ttc_eur_kwh": 0.13338}, {"timestamp": "2026-03-02T18:30:00+01:00", "spot_price": 105.67, "spot_price_eur_kwh": 0.10567, "turpe_eur_kwh": 0.0125, "accise_eur_kwh": 0.02579, "price_ht_eur_kwh": 0.14396, "price_ttc_eur_kwh": 0.17275}, {"timestamp": "2026-03-02T18:45:00+01:00", "spot_price": 126.53, "spot_price_eur_kwh": 0.12653, "turpe_eur_kwh": 0.0125, "accise_eur_kwh": 0.02579, "price_ht_eur_kwh": 0.16482, "price_ttc_eur_kwh": 0.19778}, {"timestamp": "2026-03-02T19:00:00+01:00", "spot_price": 150.73, "spot_price_eur_kwh": 0.15073, "turpe_eur_kwh": 0.0125, "accise_eur_kwh": 0.02579, "price_ht_eur_kwh": 0.18902, "price_ttc_eur_kwh": 0.22682}, {"timestamp": "2026-03-02T19:15:00+01:00", "spot_price": 132.6, "spot_price_eur_kwh": 0.1326, "turpe_eur_kwh": 0.0125, "accise_eur_kwh": 0.02579, "price_ht_eur_kwh": 0.17089, "price_ttc_eur_kwh": 0.20507}, {"timestamp": "2026-03-02T19:30:00+01:00", "spot_price": 104.8, "spot_price_eur_kwh": 0.1048, "turpe_eur_kwh": 0.0125, "accise_eur_kwh": 0.02579, "price_ht_eur_kwh": 0.14309, "price_ttc_eur_kwh": 0.17171}, {"timestamp": "2026-03-02T19:45:00+01:00", "spot_price": 87.52, "spot_price_eur_kwh": 0.08752, "turpe_eur_kwh": 0.0125, "accise_eur_kwh": 0.02579, "price_ht_eur_kwh": 0.12581, "price_ttc_eur_kwh": 0.15097}, {"timestamp": "2026-03-02T20:00:00+01:00", "spot_price": 88.75, "spot_price_eur_kwh": 0.08875, "turpe_eur_kwh": 0.0125, "accise_eur_kwh": 0.02579, "price_ht_eur_kwh": 0.12704, "price_ttc_eur_kwh": 0.15245}, {"timestamp": "2026-03-02T20:15:00+01:00", "spot_price": 87.52, "spot_price_eur_kwh": 0.08752, "turpe_eur_kwh": 0.0125, "accise_eur_kwh": 0.02579, "price_ht_eur_kwh": 0.12581, "price_ttc_eur_kwh": 0.15097}, {"timestamp": "2026-03-02T20:30:00+01:00", "spot_price": 76.46, "spot_price_eur_kwh": 0.07646, "turpe_eur_kwh": 0.0125, "accise_eur_kwh": 0.02579, "price_ht_eur_kwh": 0.11475, "price_ttc_eur_kwh": 0.1377}, {"timestamp": "2026-03-02T20:45:00+01:00", "spot_price": 67.17, "spot_price_eur_kwh": 0.06717, "turpe_eur_kwh": 0.0125, "accise_eur_kwh": 0.02579, "price_ht_eur_kwh": 0.10546, "price_ttc_eur_kwh": 0.12655}, {"timestamp": "2026-03-02T21:00:00+01:00", "spot_price": 62.93, "spot_price_eur_kwh": 0.06293, "turpe_eur_kwh": 0.0125, "accise_eur_kwh": 0.02579, "price_ht_eur_kwh": 0.10122, "price_ttc_eur_kwh": 0.12146}, {"timestamp": "2026-03-02T21:15:00+01:00", "spot_price": 56.17, "spot_price_eur_kwh": 0.05617, "turpe_eur_kwh": 0.0125, "accise_eur_kwh": 0.02579, "price_ht_eur_kwh": 0.09446, "price_ttc_eur_kwh": 0.11335}, {"timestamp": "2026-03-02T21:30:00+01:00", "spot_price": 47.25, "spot_price_eur_kwh": 0.04725, "turpe_eur_kwh": 0.0125, "accise_eur_kwh": 0.02579, "price_ht_eur_kwh": 0.08554, "price_ttc_eur_kwh": 0.10265}, {"timestamp": "2026-03-02T21:45:00+01:00", "spot_price": 37.46, "spot_price_eur_kwh": 0.03746, "turpe_eur_kwh": 0.0125, "accise_eur_kwh": 0.02579, "price_ht_eur_kwh": 0.07575, "price_ttc_eur_kwh": 0.0909}, {"timestamp": "2026-03-02T22:00:00+01:00", "spot_price": 40, "spot_price_eur_kwh": 0.04, "turpe_eur_kwh": 0.0125, "accise_eur_kwh": 0.02579, "price_ht_eur_kwh": 0.07829, "price_ttc_eur_kwh": 0.09395}, {"timestamp": "2026-03-02T22:15:00+01:00", "spot_price": 36.39, "spot_price_eur_kwh": 0.03639, "turpe_eur_kwh": 0.0125, "accise_eur_kwh": 0.02579, "price_ht_eur_kwh": 0.07468, "price_ttc_eur_kwh": 0.08962}, {"timestamp": "2026-03-02T22:30:00+01:00", "spot_price": 55.5, "spot_price_eur_kwh": 0.0555, "turpe_eur_kwh": 0.0125, "accise_eur_kwh": 0.02579, "price_ht_eur_kwh": 0.09379, "price_ttc_eur_kwh": 0.11255}, {"timestamp": "2026-03-02T22:45:00+01:00", "spot_price": 57.33, "spot_price_eur_kwh": 0.05733, "turpe_eur_kwh": 0.0125, "accise_eur_kwh": 0.02579, "price_ht_eur_kwh": 0.09562, "price_ttc_eur_kwh": 0.11474}, {"timestamp": "2026-03-02T23:00:00+01:00", "spot_price": 64.68, "spot_price_eur_kwh": 0.06468, "turpe_eur_kwh": 0.0125, "accise_eur_kwh": 0.02579, "price_ht_eur_kwh": 0.10297, "price_ttc_eur_kwh": 0.12356}, {"timestamp": "2026-03-02T23:15:00+01:00", "spot_price": 46.49, "spot_price_eur_kwh": 0.04649, "turpe_eur_kwh": 0.0125, "accise_eur_kwh": 0.02579, "price_ht_eur_kwh": 0.08478, "price_ttc_eur_kwh": 0.10174}, {"timestamp": "2026-03-02T23:30:00+01:00", "spot_price": 50.62, "spot_price_eur_kwh": 0.05062, "turpe_eur_kwh": 0.0125, "accise_eur_kwh": 0.02579, "price_ht_eur_kwh": 0.08891, "price_ttc_eur_kwh": 0.10669}, {"timestamp": "2026-03-02T23:45:00+01:00", "spot_price": 28.88, "spot_price_eur_kwh": 0.02888, "turpe_eur_kwh": 0.0125, "accise_eur_kwh": 0.02579, "price_ht_eur_kwh": 0.06717, "price_ttc_eur_kwh": 0.0806}], "pricing_metadata": {"enabled": true, "segment": "C5", "turpe_option": "LU", "profil": "pro", "display": "TTC", "tva_rate": 0.2, "accise_eur_kwh": 0.02579, "turpe_source": "table interne Sobry C5 (c\u20ac/kWh \u2192 \u20ac/kWh)", "formula_ht": "spot_price_eur_kwh + turpe_eur_kwh + accise_eur_kwh", "formula_ttc": "price_ht_eur_kwh \u00d7 (1 + TVA 20%)", "units": {"spot_price": "\u20ac/MWh", "all_other_prices": "\u20ac/kWh"}}}