{"success": true, "date": "2026-05-05", "timezone": "Europe/Paris (CET)", "count": 96, "statistics": {"min": 10.99, "max": 162.44, "average": 92.06, "median": 99}, "prices": [{"timestamp": "2026-05-05T00:00:00+02:00", "spot_price": 115.23, "spot_price_eur_kwh": 0.11523, "turpe_eur_kwh": 0.0484, "accise_eur_kwh": 0.03085, "price_ht_eur_kwh": 0.19448, "price_ttc_eur_kwh": 0.23338}, {"timestamp": "2026-05-05T00:15:00+02:00", "spot_price": 110.04, "spot_price_eur_kwh": 0.11004, "turpe_eur_kwh": 0.0484, "accise_eur_kwh": 0.03085, "price_ht_eur_kwh": 0.18929, "price_ttc_eur_kwh": 0.22715}, {"timestamp": "2026-05-05T00:30:00+02:00", "spot_price": 105.19, "spot_price_eur_kwh": 0.10519, "turpe_eur_kwh": 0.0484, "accise_eur_kwh": 0.03085, "price_ht_eur_kwh": 0.18444, "price_ttc_eur_kwh": 0.22133}, {"timestamp": "2026-05-05T00:45:00+02:00", "spot_price": 101.5, "spot_price_eur_kwh": 0.1015, "turpe_eur_kwh": 0.0484, "accise_eur_kwh": 0.03085, "price_ht_eur_kwh": 0.18075, "price_ttc_eur_kwh": 0.2169}, {"timestamp": "2026-05-05T01:00:00+02:00", "spot_price": 105.1, "spot_price_eur_kwh": 0.1051, "turpe_eur_kwh": 0.0484, "accise_eur_kwh": 0.03085, "price_ht_eur_kwh": 0.18435, "price_ttc_eur_kwh": 0.22122}, {"timestamp": "2026-05-05T01:15:00+02:00", "spot_price": 101.5, "spot_price_eur_kwh": 0.1015, "turpe_eur_kwh": 0.0484, "accise_eur_kwh": 0.03085, "price_ht_eur_kwh": 0.18075, "price_ttc_eur_kwh": 0.2169}, {"timestamp": "2026-05-05T01:30:00+02:00", "spot_price": 101.74, "spot_price_eur_kwh": 0.10174, "turpe_eur_kwh": 0.0484, "accise_eur_kwh": 0.03085, "price_ht_eur_kwh": 0.18099, "price_ttc_eur_kwh": 0.21719}, {"timestamp": "2026-05-05T01:45:00+02:00", "spot_price": 100.78, "spot_price_eur_kwh": 0.10078, "turpe_eur_kwh": 0.0484, "accise_eur_kwh": 0.03085, "price_ht_eur_kwh": 0.18003, "price_ttc_eur_kwh": 0.21604}, {"timestamp": "2026-05-05T02:00:00+02:00", "spot_price": 100.54, "spot_price_eur_kwh": 0.10054, "turpe_eur_kwh": 0.0484, "accise_eur_kwh": 0.03085, "price_ht_eur_kwh": 0.17979, "price_ttc_eur_kwh": 0.21575}, {"timestamp": "2026-05-05T02:15:00+02:00", "spot_price": 86.82, "spot_price_eur_kwh": 0.08682, "turpe_eur_kwh": 0.0484, "accise_eur_kwh": 0.03085, "price_ht_eur_kwh": 0.16607, "price_ttc_eur_kwh": 0.19928}, {"timestamp": "2026-05-05T02:30:00+02:00", "spot_price": 85, "spot_price_eur_kwh": 0.085, "turpe_eur_kwh": 0.0484, "accise_eur_kwh": 0.03085, "price_ht_eur_kwh": 0.16425, "price_ttc_eur_kwh": 0.1971}, {"timestamp": "2026-05-05T02:45:00+02:00", "spot_price": 86.39, "spot_price_eur_kwh": 0.08639, "turpe_eur_kwh": 0.0484, "accise_eur_kwh": 0.03085, "price_ht_eur_kwh": 0.16564, "price_ttc_eur_kwh": 0.19877}, {"timestamp": "2026-05-05T03:00:00+02:00", "spot_price": 87.93, "spot_price_eur_kwh": 0.08793, "turpe_eur_kwh": 0.0484, "accise_eur_kwh": 0.03085, "price_ht_eur_kwh": 0.16718, "price_ttc_eur_kwh": 0.20062}, {"timestamp": "2026-05-05T03:15:00+02:00", "spot_price": 88.32, "spot_price_eur_kwh": 0.08832, "turpe_eur_kwh": 0.0484, "accise_eur_kwh": 0.03085, "price_ht_eur_kwh": 0.16757, "price_ttc_eur_kwh": 0.20108}, {"timestamp": "2026-05-05T03:30:00+02:00", "spot_price": 96.56, "spot_price_eur_kwh": 0.09656, "turpe_eur_kwh": 0.0484, "accise_eur_kwh": 0.03085, "price_ht_eur_kwh": 0.17581, "price_ttc_eur_kwh": 0.21097}, {"timestamp": "2026-05-05T03:45:00+02:00", "spot_price": 78.29, "spot_price_eur_kwh": 0.07829, "turpe_eur_kwh": 0.0484, "accise_eur_kwh": 0.03085, "price_ht_eur_kwh": 0.15754, "price_ttc_eur_kwh": 0.18905}, {"timestamp": "2026-05-05T04:00:00+02:00", "spot_price": 91.02, "spot_price_eur_kwh": 0.09102, "turpe_eur_kwh": 0.0484, "accise_eur_kwh": 0.03085, "price_ht_eur_kwh": 0.17027, "price_ttc_eur_kwh": 0.20432}, {"timestamp": "2026-05-05T04:15:00+02:00", "spot_price": 79, "spot_price_eur_kwh": 0.079, "turpe_eur_kwh": 0.0484, "accise_eur_kwh": 0.03085, "price_ht_eur_kwh": 0.15825, "price_ttc_eur_kwh": 0.1899}, {"timestamp": "2026-05-05T04:30:00+02:00", "spot_price": 97.89, "spot_price_eur_kwh": 0.09789, "turpe_eur_kwh": 0.0484, "accise_eur_kwh": 0.03085, "price_ht_eur_kwh": 0.17714, "price_ttc_eur_kwh": 0.21257}, {"timestamp": "2026-05-05T04:45:00+02:00", "spot_price": 93.76, "spot_price_eur_kwh": 0.09376, "turpe_eur_kwh": 0.0484, "accise_eur_kwh": 0.03085, "price_ht_eur_kwh": 0.17301, "price_ttc_eur_kwh": 0.20761}, {"timestamp": "2026-05-05T05:00:00+02:00", "spot_price": 100.78, "spot_price_eur_kwh": 0.10078, "turpe_eur_kwh": 0.0484, "accise_eur_kwh": 0.03085, "price_ht_eur_kwh": 0.18003, "price_ttc_eur_kwh": 0.21604}, {"timestamp": "2026-05-05T05:15:00+02:00", "spot_price": 101, "spot_price_eur_kwh": 0.101, "turpe_eur_kwh": 0.0484, "accise_eur_kwh": 0.03085, "price_ht_eur_kwh": 0.18025, "price_ttc_eur_kwh": 0.2163}, {"timestamp": "2026-05-05T05:30:00+02:00", "spot_price": 85.87, "spot_price_eur_kwh": 0.08587, "turpe_eur_kwh": 0.0484, "accise_eur_kwh": 0.03085, "price_ht_eur_kwh": 0.16512, "price_ttc_eur_kwh": 0.19814}, {"timestamp": "2026-05-05T05:45:00+02:00", "spot_price": 94.41, "spot_price_eur_kwh": 0.09441, "turpe_eur_kwh": 0.0484, "accise_eur_kwh": 0.03085, "price_ht_eur_kwh": 0.17366, "price_ttc_eur_kwh": 0.20839}, {"timestamp": "2026-05-05T06:00:00+02:00", "spot_price": 97.8, "spot_price_eur_kwh": 0.0978, "turpe_eur_kwh": 0.0484, "accise_eur_kwh": 0.03085, "price_ht_eur_kwh": 0.17705, "price_ttc_eur_kwh": 0.21246}, {"timestamp": "2026-05-05T06:15:00+02:00", "spot_price": 101.5, "spot_price_eur_kwh": 0.1015, "turpe_eur_kwh": 0.0484, "accise_eur_kwh": 0.03085, "price_ht_eur_kwh": 0.18075, "price_ttc_eur_kwh": 0.2169}, {"timestamp": "2026-05-05T06:30:00+02:00", "spot_price": 105, "spot_price_eur_kwh": 0.105, "turpe_eur_kwh": 0.0484, "accise_eur_kwh": 0.03085, "price_ht_eur_kwh": 0.18425, "price_ttc_eur_kwh": 0.2211}, {"timestamp": "2026-05-05T06:45:00+02:00", "spot_price": 108.2, "spot_price_eur_kwh": 0.1082, "turpe_eur_kwh": 0.0484, "accise_eur_kwh": 0.03085, "price_ht_eur_kwh": 0.18745, "price_ttc_eur_kwh": 0.22494}, {"timestamp": "2026-05-05T07:00:00+02:00", "spot_price": 119.35, "spot_price_eur_kwh": 0.11935, "turpe_eur_kwh": 0.0484, "accise_eur_kwh": 0.03085, "price_ht_eur_kwh": 0.1986, "price_ttc_eur_kwh": 0.23832}, {"timestamp": "2026-05-05T07:15:00+02:00", "spot_price": 120, "spot_price_eur_kwh": 0.12, "turpe_eur_kwh": 0.0484, "accise_eur_kwh": 0.03085, "price_ht_eur_kwh": 0.19925, "price_ttc_eur_kwh": 0.2391}, {"timestamp": "2026-05-05T07:30:00+02:00", "spot_price": 119.35, "spot_price_eur_kwh": 0.11935, "turpe_eur_kwh": 0.0484, "accise_eur_kwh": 0.03085, "price_ht_eur_kwh": 0.1986, "price_ttc_eur_kwh": 0.23832}, {"timestamp": "2026-05-05T07:45:00+02:00", "spot_price": 116.5, "spot_price_eur_kwh": 0.1165, "turpe_eur_kwh": 0.0484, "accise_eur_kwh": 0.03085, "price_ht_eur_kwh": 0.19575, "price_ttc_eur_kwh": 0.2349}, {"timestamp": "2026-05-05T08:00:00+02:00", "spot_price": 120.99, "spot_price_eur_kwh": 0.12099, "turpe_eur_kwh": 0.0484, "accise_eur_kwh": 0.03085, "price_ht_eur_kwh": 0.20024, "price_ttc_eur_kwh": 0.24029}, {"timestamp": "2026-05-05T08:15:00+02:00", "spot_price": 115.29, "spot_price_eur_kwh": 0.11529, "turpe_eur_kwh": 0.0484, "accise_eur_kwh": 0.03085, "price_ht_eur_kwh": 0.19454, "price_ttc_eur_kwh": 0.23345}, {"timestamp": "2026-05-05T08:30:00+02:00", "spot_price": 109.08, "spot_price_eur_kwh": 0.10908, "turpe_eur_kwh": 0.0484, "accise_eur_kwh": 0.03085, "price_ht_eur_kwh": 0.18833, "price_ttc_eur_kwh": 0.226}, {"timestamp": "2026-05-05T08:45:00+02:00", "spot_price": 109.24, "spot_price_eur_kwh": 0.10924, "turpe_eur_kwh": 0.0484, "accise_eur_kwh": 0.03085, "price_ht_eur_kwh": 0.18849, "price_ttc_eur_kwh": 0.22619}, {"timestamp": "2026-05-05T09:00:00+02:00", "spot_price": 118, "spot_price_eur_kwh": 0.118, "turpe_eur_kwh": 0.0484, "accise_eur_kwh": 0.03085, "price_ht_eur_kwh": 0.19725, "price_ttc_eur_kwh": 0.2367}, {"timestamp": "2026-05-05T09:15:00+02:00", "spot_price": 115.34, "spot_price_eur_kwh": 0.11534, "turpe_eur_kwh": 0.0484, "accise_eur_kwh": 0.03085, "price_ht_eur_kwh": 0.19459, "price_ttc_eur_kwh": 0.23351}, {"timestamp": "2026-05-05T09:30:00+02:00", "spot_price": 105.98, "spot_price_eur_kwh": 0.10598, "turpe_eur_kwh": 0.0484, "accise_eur_kwh": 0.03085, "price_ht_eur_kwh": 0.18523, "price_ttc_eur_kwh": 0.22228}, {"timestamp": "2026-05-05T09:45:00+02:00", "spot_price": 109.52, "spot_price_eur_kwh": 0.10952, "turpe_eur_kwh": 0.0484, "accise_eur_kwh": 0.03085, "price_ht_eur_kwh": 0.18877, "price_ttc_eur_kwh": 0.22652}, {"timestamp": "2026-05-05T10:00:00+02:00", "spot_price": 123.07, "spot_price_eur_kwh": 0.12307, "turpe_eur_kwh": 0.0484, "accise_eur_kwh": 0.03085, "price_ht_eur_kwh": 0.20232, "price_ttc_eur_kwh": 0.24278}, {"timestamp": "2026-05-05T10:15:00+02:00", "spot_price": 114.65, "spot_price_eur_kwh": 0.11465, "turpe_eur_kwh": 0.0484, "accise_eur_kwh": 0.03085, "price_ht_eur_kwh": 0.1939, "price_ttc_eur_kwh": 0.23268}, {"timestamp": "2026-05-05T10:30:00+02:00", "spot_price": 102.87, "spot_price_eur_kwh": 0.10287, "turpe_eur_kwh": 0.0484, "accise_eur_kwh": 0.03085, "price_ht_eur_kwh": 0.18212, "price_ttc_eur_kwh": 0.21854}, {"timestamp": "2026-05-05T10:45:00+02:00", "spot_price": 101.2, "spot_price_eur_kwh": 0.1012, "turpe_eur_kwh": 0.0484, "accise_eur_kwh": 0.03085, "price_ht_eur_kwh": 0.18045, "price_ttc_eur_kwh": 0.21654}, {"timestamp": "2026-05-05T11:00:00+02:00", "spot_price": 110.85, "spot_price_eur_kwh": 0.11085, "turpe_eur_kwh": 0.0484, "accise_eur_kwh": 0.03085, "price_ht_eur_kwh": 0.1901, "price_ttc_eur_kwh": 0.22812}, {"timestamp": "2026-05-05T11:15:00+02:00", "spot_price": 80.9, "spot_price_eur_kwh": 0.0809, "turpe_eur_kwh": 0.0484, "accise_eur_kwh": 0.03085, "price_ht_eur_kwh": 0.16015, "price_ttc_eur_kwh": 0.19218}, {"timestamp": "2026-05-05T11:30:00+02:00", "spot_price": 81.38, "spot_price_eur_kwh": 0.08138, "turpe_eur_kwh": 0.0484, "accise_eur_kwh": 0.03085, "price_ht_eur_kwh": 0.16063, "price_ttc_eur_kwh": 0.19276}, {"timestamp": "2026-05-05T11:45:00+02:00", "spot_price": 70.43, "spot_price_eur_kwh": 0.07043, "turpe_eur_kwh": 0.0484, "accise_eur_kwh": 0.03085, "price_ht_eur_kwh": 0.14968, "price_ttc_eur_kwh": 0.17962}, {"timestamp": "2026-05-05T12:00:00+02:00", "spot_price": 90.45, "spot_price_eur_kwh": 0.09045, "turpe_eur_kwh": 0.0484, "accise_eur_kwh": 0.03085, "price_ht_eur_kwh": 0.1697, "price_ttc_eur_kwh": 0.20364}, {"timestamp": "2026-05-05T12:15:00+02:00", "spot_price": 64.58, "spot_price_eur_kwh": 0.06458, "turpe_eur_kwh": 0.0484, "accise_eur_kwh": 0.03085, "price_ht_eur_kwh": 0.14383, "price_ttc_eur_kwh": 0.1726}, {"timestamp": "2026-05-05T12:30:00+02:00", "spot_price": 78.2, "spot_price_eur_kwh": 0.0782, "turpe_eur_kwh": 0.0484, "accise_eur_kwh": 0.03085, "price_ht_eur_kwh": 0.15745, "price_ttc_eur_kwh": 0.18894}, {"timestamp": "2026-05-05T12:45:00+02:00", "spot_price": 77.68, "spot_price_eur_kwh": 0.07768, "turpe_eur_kwh": 0.0484, "accise_eur_kwh": 0.03085, "price_ht_eur_kwh": 0.15693, "price_ttc_eur_kwh": 0.18832}, {"timestamp": "2026-05-05T13:00:00+02:00", "spot_price": 85.23, "spot_price_eur_kwh": 0.08523, "turpe_eur_kwh": 0.0484, "accise_eur_kwh": 0.03085, "price_ht_eur_kwh": 0.16448, "price_ttc_eur_kwh": 0.19738}, {"timestamp": "2026-05-05T13:15:00+02:00", "spot_price": 63.65, "spot_price_eur_kwh": 0.06365, "turpe_eur_kwh": 0.0484, "accise_eur_kwh": 0.03085, "price_ht_eur_kwh": 0.1429, "price_ttc_eur_kwh": 0.17148}, {"timestamp": "2026-05-05T13:30:00+02:00", "spot_price": 54.34, "spot_price_eur_kwh": 0.05434, "turpe_eur_kwh": 0.0484, "accise_eur_kwh": 0.03085, "price_ht_eur_kwh": 0.13359, "price_ttc_eur_kwh": 0.16031}, {"timestamp": "2026-05-05T13:45:00+02:00", "spot_price": 49.96, "spot_price_eur_kwh": 0.04996, "turpe_eur_kwh": 0.0484, "accise_eur_kwh": 0.03085, "price_ht_eur_kwh": 0.12921, "price_ttc_eur_kwh": 0.15505}, {"timestamp": "2026-05-05T14:00:00+02:00", "spot_price": 74.57, "spot_price_eur_kwh": 0.07457, "turpe_eur_kwh": 0.0484, "accise_eur_kwh": 0.03085, "price_ht_eur_kwh": 0.15382, "price_ttc_eur_kwh": 0.18458}, {"timestamp": "2026-05-05T14:15:00+02:00", "spot_price": 60.91, "spot_price_eur_kwh": 0.06091, "turpe_eur_kwh": 0.0484, "accise_eur_kwh": 0.03085, "price_ht_eur_kwh": 0.14016, "price_ttc_eur_kwh": 0.16819}, {"timestamp": "2026-05-05T14:30:00+02:00", "spot_price": 81.68, "spot_price_eur_kwh": 0.08168, "turpe_eur_kwh": 0.0484, "accise_eur_kwh": 0.03085, "price_ht_eur_kwh": 0.16093, "price_ttc_eur_kwh": 0.19312}, {"timestamp": "2026-05-05T14:45:00+02:00", "spot_price": 61.4, "spot_price_eur_kwh": 0.0614, "turpe_eur_kwh": 0.0484, "accise_eur_kwh": 0.03085, "price_ht_eur_kwh": 0.14065, "price_ttc_eur_kwh": 0.16878}, {"timestamp": "2026-05-05T15:00:00+02:00", "spot_price": 94.17, "spot_price_eur_kwh": 0.09417, "turpe_eur_kwh": 0.0484, "accise_eur_kwh": 0.03085, "price_ht_eur_kwh": 0.17342, "price_ttc_eur_kwh": 0.2081}, {"timestamp": "2026-05-05T15:15:00+02:00", "spot_price": 68.04, "spot_price_eur_kwh": 0.06804, "turpe_eur_kwh": 0.0484, "accise_eur_kwh": 0.03085, "price_ht_eur_kwh": 0.14729, "price_ttc_eur_kwh": 0.17675}, {"timestamp": "2026-05-05T15:30:00+02:00", "spot_price": 37, "spot_price_eur_kwh": 0.037, "turpe_eur_kwh": 0.0484, "accise_eur_kwh": 0.03085, "price_ht_eur_kwh": 0.11625, "price_ttc_eur_kwh": 0.1395}, {"timestamp": "2026-05-05T15:45:00+02:00", "spot_price": 39.98, "spot_price_eur_kwh": 0.03998, "turpe_eur_kwh": 0.0484, "accise_eur_kwh": 0.03085, "price_ht_eur_kwh": 0.11923, "price_ttc_eur_kwh": 0.14308}, {"timestamp": "2026-05-05T16:00:00+02:00", "spot_price": 30.23, "spot_price_eur_kwh": 0.03023, "turpe_eur_kwh": 0.0484, "accise_eur_kwh": 0.03085, "price_ht_eur_kwh": 0.10948, "price_ttc_eur_kwh": 0.13138}, {"timestamp": "2026-05-05T16:15:00+02:00", "spot_price": 34.5, "spot_price_eur_kwh": 0.0345, "turpe_eur_kwh": 0.0484, "accise_eur_kwh": 0.03085, "price_ht_eur_kwh": 0.11375, "price_ttc_eur_kwh": 0.1365}, {"timestamp": "2026-05-05T16:30:00+02:00", "spot_price": 10.99, "spot_price_eur_kwh": 0.01099, "turpe_eur_kwh": 0.0484, "accise_eur_kwh": 0.03085, "price_ht_eur_kwh": 0.09024, "price_ttc_eur_kwh": 0.10829}, {"timestamp": "2026-05-05T16:45:00+02:00", "spot_price": 44.3, "spot_price_eur_kwh": 0.0443, "turpe_eur_kwh": 0.0484, "accise_eur_kwh": 0.03085, "price_ht_eur_kwh": 0.12355, "price_ttc_eur_kwh": 0.14826}, {"timestamp": "2026-05-05T17:00:00+02:00", "spot_price": 16.26, "spot_price_eur_kwh": 0.01626, "turpe_eur_kwh": 0.0484, "accise_eur_kwh": 0.03085, "price_ht_eur_kwh": 0.09551, "price_ttc_eur_kwh": 0.11461}, {"timestamp": "2026-05-05T17:15:00+02:00", "spot_price": 37.47, "spot_price_eur_kwh": 0.03747, "turpe_eur_kwh": 0.0484, "accise_eur_kwh": 0.03085, "price_ht_eur_kwh": 0.11672, "price_ttc_eur_kwh": 0.14006}, {"timestamp": "2026-05-05T17:30:00+02:00", "spot_price": 56.35, "spot_price_eur_kwh": 0.05635, "turpe_eur_kwh": 0.0484, "accise_eur_kwh": 0.03085, "price_ht_eur_kwh": 0.1356, "price_ttc_eur_kwh": 0.16272}, {"timestamp": "2026-05-05T17:45:00+02:00", "spot_price": 86.12, "spot_price_eur_kwh": 0.08612, "turpe_eur_kwh": 0.0484, "accise_eur_kwh": 0.03085, "price_ht_eur_kwh": 0.16537, "price_ttc_eur_kwh": 0.19844}, {"timestamp": "2026-05-05T18:00:00+02:00", "spot_price": 60.92, "spot_price_eur_kwh": 0.06092, "turpe_eur_kwh": 0.0484, "accise_eur_kwh": 0.03085, "price_ht_eur_kwh": 0.14017, "price_ttc_eur_kwh": 0.1682}, {"timestamp": "2026-05-05T18:15:00+02:00", "spot_price": 44.46, "spot_price_eur_kwh": 0.04446, "turpe_eur_kwh": 0.0484, "accise_eur_kwh": 0.03085, "price_ht_eur_kwh": 0.12371, "price_ttc_eur_kwh": 0.14845}, {"timestamp": "2026-05-05T18:30:00+02:00", "spot_price": 121, "spot_price_eur_kwh": 0.121, "turpe_eur_kwh": 0.0484, "accise_eur_kwh": 0.03085, "price_ht_eur_kwh": 0.20025, "price_ttc_eur_kwh": 0.2403}, {"timestamp": "2026-05-05T18:45:00+02:00", "spot_price": 162.44, "spot_price_eur_kwh": 0.16244, "turpe_eur_kwh": 0.0484, "accise_eur_kwh": 0.03085, "price_ht_eur_kwh": 0.24169, "price_ttc_eur_kwh": 0.29003}, {"timestamp": "2026-05-05T19:00:00+02:00", "spot_price": 146.03, "spot_price_eur_kwh": 0.14603, "turpe_eur_kwh": 0.0484, "accise_eur_kwh": 0.03085, "price_ht_eur_kwh": 0.22528, "price_ttc_eur_kwh": 0.27034}, {"timestamp": "2026-05-05T19:15:00+02:00", "spot_price": 153.91, "spot_price_eur_kwh": 0.15391, "turpe_eur_kwh": 0.0484, "accise_eur_kwh": 0.03085, "price_ht_eur_kwh": 0.23316, "price_ttc_eur_kwh": 0.27979}, {"timestamp": "2026-05-05T19:30:00+02:00", "spot_price": 124.55, "spot_price_eur_kwh": 0.12455, "turpe_eur_kwh": 0.0484, "accise_eur_kwh": 0.03085, "price_ht_eur_kwh": 0.2038, "price_ttc_eur_kwh": 0.24456}, {"timestamp": "2026-05-05T19:45:00+02:00", "spot_price": 123.5, "spot_price_eur_kwh": 0.1235, "turpe_eur_kwh": 0.0484, "accise_eur_kwh": 0.03085, "price_ht_eur_kwh": 0.20275, "price_ttc_eur_kwh": 0.2433}, {"timestamp": "2026-05-05T20:00:00+02:00", "spot_price": 90, "spot_price_eur_kwh": 0.09, "turpe_eur_kwh": 0.0484, "accise_eur_kwh": 0.03085, "price_ht_eur_kwh": 0.16925, "price_ttc_eur_kwh": 0.2031}, {"timestamp": "2026-05-05T20:15:00+02:00", "spot_price": 99, "spot_price_eur_kwh": 0.099, "turpe_eur_kwh": 0.0484, "accise_eur_kwh": 0.03085, "price_ht_eur_kwh": 0.17825, "price_ttc_eur_kwh": 0.2139}, {"timestamp": "2026-05-05T20:30:00+02:00", "spot_price": 106.09, "spot_price_eur_kwh": 0.10609, "turpe_eur_kwh": 0.0484, "accise_eur_kwh": 0.03085, "price_ht_eur_kwh": 0.18534, "price_ttc_eur_kwh": 0.22241}, {"timestamp": "2026-05-05T20:45:00+02:00", "spot_price": 113.35, "spot_price_eur_kwh": 0.11335, "turpe_eur_kwh": 0.0484, "accise_eur_kwh": 0.03085, "price_ht_eur_kwh": 0.1926, "price_ttc_eur_kwh": 0.23112}, {"timestamp": "2026-05-05T21:00:00+02:00", "spot_price": 110, "spot_price_eur_kwh": 0.11, "turpe_eur_kwh": 0.0484, "accise_eur_kwh": 0.03085, "price_ht_eur_kwh": 0.18925, "price_ttc_eur_kwh": 0.2271}, {"timestamp": "2026-05-05T21:15:00+02:00", "spot_price": 111.7, "spot_price_eur_kwh": 0.1117, "turpe_eur_kwh": 0.0484, "accise_eur_kwh": 0.03085, "price_ht_eur_kwh": 0.19095, "price_ttc_eur_kwh": 0.22914}, {"timestamp": "2026-05-05T21:30:00+02:00", "spot_price": 101.2, "spot_price_eur_kwh": 0.1012, "turpe_eur_kwh": 0.0484, "accise_eur_kwh": 0.03085, "price_ht_eur_kwh": 0.18045, "price_ttc_eur_kwh": 0.21654}, {"timestamp": "2026-05-05T21:45:00+02:00", "spot_price": 79.86, "spot_price_eur_kwh": 0.07986, "turpe_eur_kwh": 0.0484, "accise_eur_kwh": 0.03085, "price_ht_eur_kwh": 0.15911, "price_ttc_eur_kwh": 0.19093}, {"timestamp": "2026-05-05T22:00:00+02:00", "spot_price": 114.63, "spot_price_eur_kwh": 0.11463, "turpe_eur_kwh": 0.0484, "accise_eur_kwh": 0.03085, "price_ht_eur_kwh": 0.19388, "price_ttc_eur_kwh": 0.23266}, {"timestamp": "2026-05-05T22:15:00+02:00", "spot_price": 98.73, "spot_price_eur_kwh": 0.09873, "turpe_eur_kwh": 0.0484, "accise_eur_kwh": 0.03085, "price_ht_eur_kwh": 0.17798, "price_ttc_eur_kwh": 0.21358}, {"timestamp": "2026-05-05T22:30:00+02:00", "spot_price": 110, "spot_price_eur_kwh": 0.11, "turpe_eur_kwh": 0.0484, "accise_eur_kwh": 0.03085, "price_ht_eur_kwh": 0.18925, "price_ttc_eur_kwh": 0.2271}, {"timestamp": "2026-05-05T22:45:00+02:00", "spot_price": 105.1, "spot_price_eur_kwh": 0.1051, "turpe_eur_kwh": 0.0484, "accise_eur_kwh": 0.03085, "price_ht_eur_kwh": 0.18435, "price_ttc_eur_kwh": 0.22122}, {"timestamp": "2026-05-05T23:00:00+02:00", "spot_price": 105.92, "spot_price_eur_kwh": 0.10592, "turpe_eur_kwh": 0.0484, "accise_eur_kwh": 0.03085, "price_ht_eur_kwh": 0.18517, "price_ttc_eur_kwh": 0.2222}, {"timestamp": "2026-05-05T23:15:00+02:00", "spot_price": 91.39, "spot_price_eur_kwh": 0.09139, "turpe_eur_kwh": 0.0484, "accise_eur_kwh": 0.03085, "price_ht_eur_kwh": 0.17064, "price_ttc_eur_kwh": 0.20477}, {"timestamp": "2026-05-05T23:30:00+02:00", "spot_price": 101.44, "spot_price_eur_kwh": 0.10144, "turpe_eur_kwh": 0.0484, "accise_eur_kwh": 0.03085, "price_ht_eur_kwh": 0.18069, "price_ttc_eur_kwh": 0.21683}, {"timestamp": "2026-05-05T23:45:00+02:00", "spot_price": 92.94, "spot_price_eur_kwh": 0.09294, "turpe_eur_kwh": 0.0484, "accise_eur_kwh": 0.03085, "price_ht_eur_kwh": 0.17219, "price_ttc_eur_kwh": 0.20663}], "pricing_metadata": {"enabled": true, "segment": "C5", "turpe_option": "CU", "profil": "particulier", "display": "TTC", "tva_rate": 0.2, "accise_eur_kwh": 0.03085, "turpe_source": "table interne Sobry C5 (c\u20ac/kWh \u2192 \u20ac/kWh)", "formula_ht": "spot_price_eur_kwh + turpe_eur_kwh + accise_eur_kwh", "formula_ttc": "price_ht_eur_kwh \u00d7 (1 + TVA 20%)", "units": {"spot_price": "\u20ac/MWh", "all_other_prices": "\u20ac/kWh"}}}